nunit/__init__.py
nunit/au.py
nunit/constant.py
nunit/version.py
nunit-0.0.3.dist-info/DESCRIPTION.rst
nunit-0.0.3.dist-info/METADATA
nunit-0.0.3.dist-info/RECORD
nunit-0.0.3.dist-info/WHEEL
nunit-0.0.3.dist-info/metadata.json
nunit-0.0.3.dist-info/top_level.txt
