Metadata-Version: 2.0
Name: nunit
Version: 0.0.3
Summary: Tools for natural unit system in physics
Home-page: UNKNOWN
Author: sahn
Author-email: jam31118@gmail.com
License: GPLv3
Keywords: unit,physics,atomic unit,natural unit
Platform: UNKNOWN
Classifier: Topic :: Scientific/Engineering :: Physics
Classifier: License :: OSI Approved :: GNU Affero General Public License v3
Classifier: Programming Language :: Python :: 3.5
Classifier: Programming Language :: Python :: 3.6
